torchtest/__init__.py
torchtest/torchtest.py
torchtest-0.5.dist-info/DESCRIPTION.rst
torchtest-0.5.dist-info/METADATA
torchtest-0.5.dist-info/RECORD
torchtest-0.5.dist-info/WHEEL
torchtest-0.5.dist-info/metadata.json
torchtest-0.5.dist-info/top_level.txt
