Metadata-Version: 2.0
Name: torchtest
Version: 0.5
Summary: UNKNOWN
Home-page: UNKNOWN
Author: UNKNOWN
Author-email: UNKNOWN
License: GNU Affero General Public License v3 or later (AGPLv3+)
Platform: UNKNOWN
Requires-Dist: torch
